README.md
pyproject.toml
setup.py
LiteVkApi/__init__.py
LiteVkApi.egg-info/PKG-INFO
LiteVkApi.egg-info/SOURCES.txt
LiteVkApi.egg-info/dependency_links.txt
LiteVkApi.egg-info/not-zip-safe
LiteVkApi.egg-info/requires.txt
LiteVkApi.egg-info/top_level.txt