Metadata-Version: 2.1
Name: LiteVkApi
Version: 2.4.1
Summary: Библиотека для легкого написания ботов ВК!
Home-page: UNKNOWN
Author-email: ma_mush@mail.ru
License: UNKNOWN
Platform: UNKNOWN
Requires-Python: >=3.8
